{
  "title": "NY Times, Monday, April 8, 2024",
  "author": "Christina Iverson / Sam Ezersky",
  "editor": "Will Shortz",
  "copyright": "\u00a9 2024, The New York Times",
  "publisher": "The New York Times",
  "date": "08/04/2024",
  "notepad": null,
  "jnotes": null,
  "shadecircles": null,
  "interpretcolors": null,
  "key": null,
  "hold": null,
  "track": null,
  "autowrap": null,
  "mini": null,
  "id": null,
  "id2": null,
  "code": null,
  "dow": "Friday",
  "type": null,
  "valid": true,
  "uniclue": false,
  "admin": false,
  "hastitle": false,
  "navigate": true,
  "auto": false,
  "size": {
    "rows": 5,
    "cols": 5
  },
  "grid": [
    "O",
    "P",
    "S",
    ".",
    ".",
    "L",
    "O",
    "O",
    "T",
    ".",
    "D",
    "E",
    "L",
    "H",
    "I",
    ".",
    "M",
    "O",
    "O",
    "N",
    ".",
    ".",
    "S",
    "U",
    "N"
  ],
  "gridnums": [
    1,
    2,
    3,
    0,
    0,
    4,
    0,
    0,
    5,
    0,
    6,
    0,
    0,
    0,
    7,
    0,
    8,
    0,
    0,
    0,
    0,
    0,
    9,
    0,
    0
  ],
  "circles": null,
  "acrossmap": null,
  "downmap": null,
  "rbars": null,
  "bbars": null,
  "clues": {
    "across": [
      "1. Black ___ (military missions)",
      "4. Pirate's booty",
      "6. New ___, capital of India",
      "8. On average, it's roughly 239,000 miles from Earth",
      "9. What's been fully \"eclipsed\" by 8-Across in this puzzle"
    ],
    "down": [
      "1. Getting up there in years",
      "2. Robert Bly wrote one called \"Seeing the Eclipse in Maine\"",
      "3. Times for musicians to shine",
      "5. Biblical \"you\"",
      "7. Traveler's stopover"
    ]
  },
  "answers": {
    "across": [
      "OPS",
      "LOOT",
      "DELHI",
      "MOON",
      "SUN"
    ],
    "down": [
      "OLD",
      "POEM",
      "SOLOS",
      "THOU",
      "INN"
    ]
  }
}2024-08-04 02:05:05,129:INFO - HTTP Request: POST https://hetszssurnrltpueswfq.supabase.co/rest/v1/puzzles "HTTP/1.1 201 Created"
{
  "title": "NY Times, Sunday, August 4, 2024",
  "author": "Christina Iverson / Sam Ezersky",
  "editor": "Will Shortz",
  "copyright": "\u00a9 2024, The New York Times",
  "publisher": "The New York Times",
  "date": "04/08/2024",
  "notepad": null,
  "jnotes": null,
  "shadecircles": null,
  "interpretcolors": null,
  "key": null,
  "hold": null,
  "track": null,
  "autowrap": null,
  "mini": null,
  "id": null,
  "id2": null,
  "code": null,
  "dow": "Friday",
  "type": null,
  "valid": true,
  "uniclue": false,
  "admin": false,
  "hastitle": false,
  "navigate": true,
  "auto": false,
  "size": {
    "rows": 5,
    "cols": 5
  },
  "grid": [
    ".",
    "H",
    "E",
    "A",
    "D",
    "B",
    "I",
    "L",
    "B",
    "O",
    "U",
    "P",
    "S",
    "E",
    "T",
    "S",
    "P",
    "I",
    "T",
    "E",
    "T",
    "O",
    "E",
    ".",
    "."
  ],
  "gridnums": [
    0,
    1,
    2,
    3,
    4,
    5,
    0,
    0,
    0,
    0,
    6,
    0,
    0,
    0,
    0,
    7,
    0,
    0,
    0,
    0,
    8,
    0,
    0,
    0,
    0
  ],
  "circles": null,
  "acrossmap": null,
  "downmap": null,
  "rbars": null,
  "bbars": null,
  "clues": {
    "across": [
      "1. The first blank in this phrase: From ___ to ___",
      "5. \"The Hobbit\" hobbit",
      "6. A 16 seed beating a 1 seed, e.g.",
      "7. Feeling of ill will",
      "8. The second blank in this phrase: From ___ to ___"
    ],
    "down": [
      "1. Creature able to hold its breath underwater for up to 30 minutes",
      "2. Name that sounds like the twelfth and third letters of the alphabet",
      "3. Help with a crime",
      "4. Pour love (on)",
      "5. Opposite of boom, on Wall Street"
    ]
  },
  "answers": {
    "across": [
      "HEAD",
      "BILBO",
      "UPSET",
      "SPITE",
      "TOE"
    ],
    "down": [
      "BUST",
      "HIPPO",
      "ELSIE",
      "ABET",
      "DOTE"
    ]
  }
}
